{
  "updated_at": "2026-06-23T08:02:36.867016+09:00",
  "today": "2026-06-23",
  "books": [
    {
      "title": "Famous For My Dinner Parties #4 2026",
      "store": "Do you read me?!",
      "city": "베를린",
      "section": "잡지·아트북",
      "author": "FFDP",
      "store_cover": "https://cdn.shopify.com/s/files/1/0726/7500/0664/files/43540-Famous-For-My-Dinner-Parties-4-2026-1.jpg?v=1782121558",
      "store_link": "https://www.doyoureadme.de/products/famous-for-my-dinner-parties-4-2026",
      "published_at": "2026-06-22T11:48:39+02:00",
      "cover": "https://cdn.shopify.com/s/files/1/0726/7500/0664/files/43540-Famous-For-My-Dinner-Parties-4-2026-1.jpg?v=1782121558"
    },
    {
      "title": "PDF Magazine #1 2026",
      "store": "Do you read me?!",
      "city": "베를린",
      "section": "잡지·아트북",
      "author": "Luke Abby Studio",
      "store_cover": "https://cdn.shopify.com/s/files/1/0726/7500/0664/files/43535-PDF-Magazine-1-2026-1.jpg?v=1782121559",
      "store_link": "https://www.doyoureadme.de/products/pdf-1-2026",
      "published_at": "2026-06-22T11:48:39+02:00",
      "cover": "https://cdn.shopify.com/s/files/1/0726/7500/0664/files/43535-PDF-Magazine-1-2026-1.jpg?v=1782121559"
    },
    {
      "title": "Autre #22 S/S 2026",
      "store": "Do you read me?!",
      "city": "베를린",
      "section": "잡지·아트북",
      "author": "Autre Magazine",
      "store_cover": "https://cdn.shopify.com/s/files/1/0726/7500/0664/files/43534-Autre-22-SS-2026-1.jpg?v=1782121559",
      "store_link": "https://www.doyoureadme.de/products/autre-22-s-s-2026",
      "published_at": "2026-06-22T11:48:39+02:00",
      "cover": "https://cdn.shopify.com/s/files/1/0726/7500/0664/files/43534-Autre-22-SS-2026-1.jpg?v=1782121559"
    },
    {
      "title": "Numero Homme Berlin #24 2026",
      "store": "Do you read me?!",
      "city": "베를린",
      "section": "잡지·아트북",
      "author": "Off One's Rocker Publishing LTD.",
      "store_cover": "https://cdn.shopify.com/s/files/1/0726/7500/0664/files/43533-Numero-Homme-Berlin-24-2026-1.jpg?v=1782121559",
      "store_link": "https://www.doyoureadme.de/products/numero-homme-berlin-24-2026",
      "published_at": "2026-06-22T11:48:39+02:00",
      "cover": "https://cdn.shopify.com/s/files/1/0726/7500/0664/files/43533-Numero-Homme-Berlin-24-2026-1.jpg?v=1782121559"
    },
    {
      "title": "Vogue USA May 2026",
      "store": "Do you read me?!",
      "city": "베를린",
      "section": "잡지·아트북",
      "author": "Condé Nast",
      "store_cover": "https://cdn.shopify.com/s/files/1/0726/7500/0664/files/Vogue_Standard_e289ef4c-220b-41ff-a692-c56f195833c5.jpg?v=1730212917",
      "store_link": "https://www.doyoureadme.de/products/vogue-usa-may-2026",
      "published_at": "2026-06-20T16:58:40+02:00",
      "cover": "https://cdn.shopify.com/s/files/1/0726/7500/0664/files/Vogue_Standard_e289ef4c-220b-41ff-a692-c56f195833c5.jpg?v=1730212917"
    },
    {
      "title": "Scenery #5 2026",
      "store": "Do you read me?!",
      "city": "베를린",
      "section": "잡지·아트북",
      "author": "Scenery Magazine",
      "store_cover": "https://cdn.shopify.com/s/files/1/0726/7500/0664/files/43531-Scenery-4-2026-1.jpg?v=1782121559",
      "store_link": "https://www.doyoureadme.de/products/scenery-4-2026",
      "published_at": "2026-06-19T11:36:33+02:00",
      "cover": "https://cdn.shopify.com/s/files/1/0726/7500/0664/files/43531-Scenery-4-2026-1.jpg?v=1782121559"
    },
    {
      "title": "King Kong #21 S/S 2026",
      "store": "Do you read me?!",
      "city": "베를린",
      "section": "잡지·아트북",
      "author": "King Kong",
      "store_cover": "https://cdn.shopify.com/s/files/1/0726/7500/0664/files/King-Kong-SS26-1.jpg?v=1781772483",
      "store_link": "https://www.doyoureadme.de/products/king-kong-21-s-s-2026",
      "published_at": "2026-06-18T11:31:02+02:00",
      "cover": "https://cdn.shopify.com/s/files/1/0726/7500/0664/files/King-Kong-SS26-1.jpg?v=1781772483"
    },
    {
      "title": "100 Beste Plakate 25",
      "store": "Do you read me?!",
      "city": "베를린",
      "section": "잡지·아트북",
      "author": "Slanted",
      "store_cover": "https://cdn.shopify.com/s/files/1/0726/7500/0664/files/100-Beste-Plakate-1.jpg?v=1781515555",
      "store_link": "https://www.doyoureadme.de/products/100-beste-plakate-25",
      "published_at": "2026-06-18T11:25:35+02:00",
      "cover": "https://cdn.shopify.com/s/files/1/0726/7500/0664/files/100-Beste-Plakate-1.jpg?v=1781515555"
    },
    {
      "title": "UN/SEEN: Women in Graphic Design up to the Bauhaus",
      "store": "Do you read me?!",
      "city": "베를린",
      "section": "잡지·아트북",
      "author": "Slanted",
      "store_cover": "https://cdn.shopify.com/s/files/1/0726/7500/0664/files/Un-Seen-1.jpg?v=1781515555",
      "store_link": "https://www.doyoureadme.de/products/un-seen-women-in-graphic-design-up-to-the-bauhaus",
      "published_at": "2026-06-18T11:22:12+02:00",
      "cover": "https://cdn.shopify.com/s/files/1/0726/7500/0664/files/Un-Seen-1.jpg?v=1781515555"
    },
    {
      "title": "Cara #3 2025",
      "store": "Do you read me?!",
      "city": "베를린",
      "section": "잡지·아트북",
      "author": "KD Presse",
      "store_cover": "https://cdn.shopify.com/s/files/1/0726/7500/0664/files/43510-Cara-3-2025-1.jpg?v=1781772483",
      "store_link": "https://www.doyoureadme.de/products/cara-3-2025",
      "published_at": "2026-06-18T11:01:17+02:00",
      "cover": "https://cdn.shopify.com/s/files/1/0726/7500/0664/files/43510-Cara-3-2025-1.jpg?v=1781772483"
    },
    {
      "title": "Cantik Manis - A Sweet Treat by Rahel Stephanie",
      "store": "Do you read me?!",
      "city": "베를린",
      "section": "잡지·아트북",
      "author": "self published",
      "store_cover": "https://cdn.shopify.com/s/files/1/0726/7500/0664/files/43519-Cantik-Manis_A-Sweet-Treat-by-Rahel-Stephanie-1.jpg?v=1781772483",
      "store_link": "https://www.doyoureadme.de/products/cantik-manis-a-sweet-treat-by-rahel-stephanie",
      "published_at": "2026-06-18T11:01:16+02:00",
      "cover": "https://cdn.shopify.com/s/files/1/0726/7500/0664/files/43519-Cantik-Manis_A-Sweet-Treat-by-Rahel-Stephanie-1.jpg?v=1781772483"
    },
    {
      "title": "Bellissimo #5 - Ireland/Mistico",
      "store": "Do you read me?!",
      "city": "베를린",
      "section": "잡지·아트북",
      "author": "Bellissimo",
      "store_cover": "https://cdn.shopify.com/s/files/1/0726/7500/0664/files/43518-Bellissimo-5_Ireland-Mistico-1.jpg?v=1781772483",
      "store_link": "https://www.doyoureadme.de/products/bellissimo-5-ireland-mistico",
      "published_at": "2026-06-18T11:01:16+02:00",
      "cover": "https://cdn.shopify.com/s/files/1/0726/7500/0664/files/43518-Bellissimo-5_Ireland-Mistico-1.jpg?v=1781772483"
    },
    {
      "title": "Bellissimo #4 - Holiday Club",
      "store": "Do you read me?!",
      "city": "베를린",
      "section": "잡지·아트북",
      "author": "Bellissimo",
      "store_cover": "https://cdn.shopify.com/s/files/1/0726/7500/0664/files/43517-Bellissimo-4_Holiday-Club-1.jpg?v=1781772483",
      "store_link": "https://www.doyoureadme.de/products/bellissimo-4-holiday-club",
      "published_at": "2026-06-18T11:01:16+02:00",
      "cover": "https://cdn.shopify.com/s/files/1/0726/7500/0664/files/43517-Bellissimo-4_Holiday-Club-1.jpg?v=1781772483"
    },
    {
      "title": "How To See Like A Machine - Trevor Paglen",
      "store": "Do you read me?!",
      "city": "베를린",
      "section": "잡지·아트북",
      "author": "Verso",
      "store_cover": "https://cdn.shopify.com/s/files/1/0726/7500/0664/files/43515-How-To-See-Like-A-Machine_Trevor-Paglen-1.jpg?v=1781772484",
      "store_link": "https://www.doyoureadme.de/products/how-to-see-like-a-machine-trevor-paglen",
      "published_at": "2026-06-18T11:01:16+02:00",
      "cover": "https://cdn.shopify.com/s/files/1/0726/7500/0664/files/43515-How-To-See-Like-A-Machine_Trevor-Paglen-1.jpg?v=1781772484"
    },
    {
      "title": "Revue #21 S/S 2026",
      "store": "Do you read me?!",
      "city": "베를린",
      "section": "잡지·아트북",
      "author": "Revue",
      "store_cover": "https://cdn.shopify.com/s/files/1/0726/7500/0664/files/43514-Revue-21-SS-2026-1.jpg?v=1781772484",
      "store_link": "https://www.doyoureadme.de/products/revue-21-s-s-2026",
      "published_at": "2026-06-18T11:01:16+02:00",
      "cover": "https://cdn.shopify.com/s/files/1/0726/7500/0664/files/43514-Revue-21-SS-2026-1.jpg?v=1781772484"
    },
    {
      "title": "Luncheon #21 2026",
      "store": "Do you read me?!",
      "city": "베를린",
      "section": "잡지·아트북",
      "author": "Luncheon Editions",
      "store_cover": "https://cdn.shopify.com/s/files/1/0726/7500/0664/files/43513-Luncheon-21-2026-1.jpg?v=1781772483",
      "store_link": "https://www.doyoureadme.de/products/luncheon-21-2026",
      "published_at": "2026-06-18T11:01:16+02:00",
      "cover": "https://cdn.shopify.com/s/files/1/0726/7500/0664/files/43513-Luncheon-21-2026-1.jpg?v=1781772483"
    },
    {
      "title": "A Manual for Living Curated for Nike - A Magazine Curated By...",
      "store": "Do you read me?!",
      "city": "베를린",
      "section": "잡지·아트북",
      "author": "A Magazine",
      "store_cover": "https://cdn.shopify.com/s/files/1/0726/7500/0664/files/43512-A-Manual-for-Living-Curated-for-Nike_A-Magazine-Curated-By.-1.jpg?v=1781772483",
      "store_link": "https://www.doyoureadme.de/products/a-manual-for-living-curated-for-nike-a-magazine-curated-by",
      "published_at": "2026-06-18T11:01:16+02:00",
      "cover": "https://cdn.shopify.com/s/files/1/0726/7500/0664/files/43512-A-Manual-for-Living-Curated-for-Nike_A-Magazine-Curated-By.-1.jpg?v=1781772483"
    },
    {
      "title": "Printing Fashion #6 2026",
      "store": "Do you read me?!",
      "city": "베를린",
      "section": "잡지·아트북",
      "author": "Printing Fashion Festival",
      "store_cover": "https://cdn.shopify.com/s/files/1/0726/7500/0664/files/43511-Printing-Fashion-6-2026-1.jpg?v=1781772484",
      "store_link": "https://www.doyoureadme.de/products/printing-fashion-6-2026",
      "published_at": "2026-06-18T11:01:16+02:00",
      "cover": "https://cdn.shopify.com/s/files/1/0726/7500/0664/files/43511-Printing-Fashion-6-2026-1.jpg?v=1781772484"
    },
    {
      "title": "Frutik",
      "store": "Do you read me?!",
      "city": "베를린",
      "section": "잡지·아트북",
      "author": "Can Can Press",
      "store_cover": "https://cdn.shopify.com/s/files/1/0726/7500/0664/files/43524-Frutik-1.jpg?v=1781772483",
      "store_link": "https://www.doyoureadme.de/products/frutik",
      "published_at": "2026-06-18T11:01:15+02:00",
      "cover": "https://cdn.shopify.com/s/files/1/0726/7500/0664/files/43524-Frutik-1.jpg?v=1781772483"
    },
    {
      "title": "Food Vol. 1 - Sessions Arts Club",
      "store": "Do you read me?!",
      "city": "베를린",
      "section": "잡지·아트북",
      "author": "Cabin Press",
      "store_cover": "https://cdn.shopify.com/s/files/1/0726/7500/0664/files/43523-Food-Vol-1_Sessions-Arts-Club-1.jpg?v=1781772483",
      "store_link": "https://www.doyoureadme.de/products/food-vol-1-sessions-arts-club",
      "published_at": "2026-06-18T11:01:15+02:00",
      "cover": "https://cdn.shopify.com/s/files/1/0726/7500/0664/files/43523-Food-Vol-1_Sessions-Arts-Club-1.jpg?v=1781772483"
    },
    {
      "title": "USSR 1991 by Keizo Kitajima (signed)",
      "store": "Donlon Books",
      "city": "런던",
      "section": "아트·사진",
      "author": "Donlon Books",
      "store_cover": "https://cdn.shopify.com/s/files/1/0221/7340/files/Screenshot2026-06-17at14.07.51.png?v=1781701968",
      "store_link": "https://donlonbooks.com/products/ussr-1991-by-keizo-kitajima-signed",
      "published_at": "2026-06-17T14:13:24+01:00",
      "cover": "https://cdn.shopify.com/s/files/1/0221/7340/files/Screenshot2026-06-17at14.07.51.png?v=1781701968"
    },
    {
      "title": "Bator zine (full set)",
      "store": "Donlon Books",
      "city": "런던",
      "section": "아트·사진",
      "author": "Donlon Books",
      "store_cover": "https://cdn.shopify.com/s/files/1/0221/7340/files/IMG_4367.heic?v=1781453915",
      "store_link": "https://donlonbooks.com/products/bator-zine-full-set",
      "published_at": "2026-06-14T15:08:05+01:00",
      "cover": "https://cdn.shopify.com/s/files/1/0221/7340/files/IMG_4367.heic?v=1781453915"
    },
    {
      "title": "Cruising Archaeology II: Eurotrash",
      "store": "Donlon Books",
      "city": "런던",
      "section": "아트·사진",
      "author": "Donlon Books",
      "store_cover": "https://cdn.shopify.com/s/files/1/0221/7340/files/Cover_23e0b965-ab74-420f-aa6a-00721856d4f7.jpg?v=1781109139",
      "store_link": "https://donlonbooks.com/products/cruising-archaeology-ii-eurotrash",
      "published_at": "2026-06-10T17:32:55+01:00",
      "cover": "https://cdn.shopify.com/s/files/1/0221/7340/files/Cover_23e0b965-ab74-420f-aa6a-00721856d4f7.jpg?v=1781109139"
    },
    {
      "title": "Elsewhere: The story of UK skateboarding 1987–2002",
      "store": "Donlon Books",
      "city": "런던",
      "section": "아트·사진",
      "author": "Donlon Books",
      "store_cover": "https://cdn.shopify.com/s/files/1/0221/7340/files/Screenshot2026-06-03at16.41.45.png?v=1780501552",
      "store_link": "https://donlonbooks.com/products/elsewhere-the-story-of-uk-skateboarding-1987-2002",
      "published_at": "2026-06-03T16:47:15+01:00",
      "cover": "https://cdn.shopify.com/s/files/1/0221/7340/files/Screenshot2026-06-03at16.41.45.png?v=1780501552"
    },
    {
      "title": "Jan Kempenaers - Memorials",
      "store": "Donlon Books",
      "city": "런던",
      "section": "아트·사진",
      "author": "Donlon Books",
      "store_cover": "https://cdn.shopify.com/s/files/1/0221/7340/files/Screenshot2026-06-03at16.33.24.png?v=1780501154",
      "store_link": "https://donlonbooks.com/products/jan-kempenaers-memorials",
      "published_at": "2026-06-03T16:39:32+01:00",
      "cover": "https://cdn.shopify.com/s/files/1/0221/7340/files/Screenshot2026-06-03at16.33.24.png?v=1780501154"
    },
    {
      "title": "Alexandre Girard's Imagined Worlds",
      "store": "Donlon Books",
      "city": "런던",
      "section": "아트·사진",
      "author": "Donlon Books",
      "store_cover": "https://cdn.shopify.com/s/files/1/0221/7340/files/Screenshot2026-06-03at16.26.18.png?v=1780500613",
      "store_link": "https://donlonbooks.com/products/alexandre-girards-imagined-worlds",
      "published_at": "2026-06-03T16:30:39+01:00",
      "cover": "https://cdn.shopify.com/s/files/1/0221/7340/files/Screenshot2026-06-03at16.26.18.png?v=1780500613"
    },
    {
      "title": "London’s Ours! Images From The Greater London Council 1981–1986 by Hazel Atashroo",
      "store": "Donlon Books",
      "city": "런던",
      "section": "아트·사진",
      "author": "Donlon Books",
      "store_cover": "https://cdn.shopify.com/s/files/1/0221/7340/files/Screenshot2026-05-17at13.21.49.png?v=1779020792",
      "store_link": "https://donlonbooks.com/products/london-s-ours-images-from-the-greater-london-council-1981-1986-by-hazel-atashroo",
      "published_at": "2026-05-17T13:29:13+01:00",
      "cover": "https://cdn.shopify.com/s/files/1/0221/7340/files/Screenshot2026-05-17at13.21.49.png?v=1779020792"
    },
    {
      "title": "Hujar:Contact",
      "store": "Donlon Books",
      "city": "런던",
      "section": "아트·사진",
      "author": "Donlon Books",
      "store_cover": "https://cdn.shopify.com/s/files/1/0221/7340/files/Screenshot2026-05-17at12.30.36.png?v=1779017447",
      "store_link": "https://donlonbooks.com/products/hujar-contact",
      "published_at": "2026-05-17T12:31:27+01:00",
      "cover": "https://cdn.shopify.com/s/files/1/0221/7340/files/Screenshot2026-05-17at12.30.36.png?v=1779017447"
    },
    {
      "title": "Cruising Pavilion: Architecture, Dissident Sex and Cruising Cultures",
      "store": "Donlon Books",
      "city": "런던",
      "section": "아트·사진",
      "author": "Donlon Books",
      "store_cover": "https://cdn.shopify.com/s/files/1/0221/7340/files/27df3ccd59.jpg?v=1779017894",
      "store_link": "https://donlonbooks.com/products/cruising-pavilion-architecture-dissident-sex-and-cruising-cultures",
      "published_at": "2026-05-17T12:17:55+01:00",
      "cover": "https://cdn.shopify.com/s/files/1/0221/7340/files/27df3ccd59.jpg?v=1779017894"
    },
    {
      "title": "fierce pussy",
      "store": "Donlon Books",
      "city": "런던",
      "section": "아트·사진",
      "author": "Donlon Books",
      "store_cover": "https://cdn.shopify.com/s/files/1/0221/7340/files/Screenshot2026-05-17at12.04.15.png?v=1779016149",
      "store_link": "https://donlonbooks.com/products/fierce-pussy",
      "published_at": "2026-05-17T12:09:35+01:00",
      "cover": "https://cdn.shopify.com/s/files/1/0221/7340/files/Screenshot2026-05-17at12.04.15.png?v=1779016149"
    },
    {
      "title": "Sex, Clubs, Dissent: Visualising Queer Nightlife by Amelia Abraham",
      "store": "Donlon Books",
      "city": "런던",
      "section": "아트·사진",
      "author": "Donlon Books",
      "store_cover": "https://cdn.shopify.com/s/files/1/0221/7340/files/Screenshot2026-05-10at16.19.03.png?v=1778426507",
      "store_link": "https://donlonbooks.com/products/sex-clubs-dissent-visualising-queer-nightlife-by-amelia-abraham",
      "published_at": "2026-05-10T16:26:43+01:00",
      "cover": "https://cdn.shopify.com/s/files/1/0221/7340/files/Screenshot2026-05-10at16.19.03.png?v=1778426507"
    },
    {
      "title": "Navy Gear by Aota Mitsuhiro",
      "store": "Donlon Books",
      "city": "런던",
      "section": "아트·사진",
      "author": "Donlon Books",
      "store_cover": "https://cdn.shopify.com/s/files/1/0221/7340/files/s-l1600_cde165ef-afd5-4886-8674-09548b0e0dff.webp?v=1777470254",
      "store_link": "https://donlonbooks.com/products/navy-gear-by-aota-mitsuhiro",
      "published_at": "2026-04-29T14:36:11+01:00",
      "cover": "https://cdn.shopify.com/s/files/1/0221/7340/files/s-l1600_cde165ef-afd5-4886-8674-09548b0e0dff.webp?v=1777470254"
    },
    {
      "title": "Jack Davison: A is for Ant Children's Edition",
      "store": "Donlon Books",
      "city": "런던",
      "section": "아트·사진",
      "author": "Donlon Books",
      "store_cover": "https://cdn.shopify.com/s/files/1/0221/7340/files/Screenshot2026-04-29at14.19.16.png?v=1777469113",
      "store_link": "https://donlonbooks.com/products/jack-davison-a-is-for-ant-childrens-edition",
      "published_at": "2026-04-29T14:26:53+01:00",
      "cover": "https://cdn.shopify.com/s/files/1/0221/7340/files/Screenshot2026-04-29at14.19.16.png?v=1777469113"
    },
    {
      "title": "Design & Visual Communication by Bruno Munari",
      "store": "Donlon Books",
      "city": "런던",
      "section": "아트·사진",
      "author": "Donlon Books",
      "store_cover": "https://cdn.shopify.com/s/files/1/0221/7340/files/51giUvGTsxL._AC_UF894_1000_QL80.jpg?v=1777468309",
      "store_link": "https://donlonbooks.com/products/design-visual-communication-by-bruno-munari",
      "published_at": "2026-04-29T14:12:18+01:00",
      "cover": "https://cdn.shopify.com/s/files/1/0221/7340/files/51giUvGTsxL._AC_UF894_1000_QL80.jpg?v=1777468309"
    },
    {
      "title": "An Archive by Edmund de Waal",
      "store": "Donlon Books",
      "city": "런던",
      "section": "아트·사진",
      "author": "Donlon Books",
      "store_cover": "https://cdn.shopify.com/s/files/1/0221/7340/files/Screenshot2026-04-29at14.00.26.png?v=1777467644",
      "store_link": "https://donlonbooks.com/products/an-archive-by-edmund-de-waal",
      "published_at": "2026-04-29T14:07:49+01:00",
      "cover": "https://cdn.shopify.com/s/files/1/0221/7340/files/Screenshot2026-04-29at14.00.26.png?v=1777467644"
    },
    {
      "title": "Sausage and Custard by Roxy Lee",
      "store": "Donlon Books",
      "city": "런던",
      "section": "아트·사진",
      "author": "Donlon Books",
      "store_cover": "https://cdn.shopify.com/s/files/1/0221/7340/files/WhatsAppImage2026-04-29at13.57.57.jpg?v=1777467528",
      "store_link": "https://donlonbooks.com/products/sausage-and-custard-by-roxy-lee",
      "published_at": "2026-04-29T13:59:55+01:00",
      "cover": "https://cdn.shopify.com/s/files/1/0221/7340/files/WhatsAppImage2026-04-29at13.57.57.jpg?v=1777467528"
    },
    {
      "title": "Discomania by Jennifer Gibbons (Signed - Limited Edition)",
      "store": "Donlon Books",
      "city": "런던",
      "section": "아트·사진",
      "author": "Donlon Books",
      "store_cover": "https://cdn.shopify.com/s/files/1/0221/7340/files/discomania_web.jpg?v=1777217984",
      "store_link": "https://donlonbooks.com/products/discomania-by-jennifer-gibbons",
      "published_at": "2026-04-26T16:43:11+01:00",
      "cover": "https://cdn.shopify.com/s/files/1/0221/7340/files/discomania_web.jpg?v=1777217984"
    },
    {
      "title": "The Megalithic Imperative",
      "store": "Donlon Books",
      "city": "런던",
      "section": "아트·사진",
      "author": "Donlon Books",
      "store_cover": "https://cdn.shopify.com/s/files/1/0221/7340/files/Megalithic-Imperative-web.jpg?v=1777217524",
      "store_link": "https://donlonbooks.com/products/the-megalithic-imperative",
      "published_at": "2026-04-26T16:37:08+01:00",
      "cover": "https://cdn.shopify.com/s/files/1/0221/7340/files/Megalithic-Imperative-web.jpg?v=1777217524"
    },
    {
      "title": "Valie Export: Archive Matters",
      "store": "Donlon Books",
      "city": "런던",
      "section": "아트·사진",
      "author": "Donlon Books",
      "store_cover": "https://cdn.shopify.com/s/files/1/0221/7340/files/csm_Archive_Matters_Cover_14_9_2021_s_Seite_1_ac24a68f78.jpg?v=1776875285",
      "store_link": "https://donlonbooks.com/products/valie-export-archive-matters",
      "published_at": "2026-04-22T17:29:30+01:00",
      "cover": "https://cdn.shopify.com/s/files/1/0221/7340/files/csm_Archive_Matters_Cover_14_9_2021_s_Seite_1_ac24a68f78.jpg?v=1776875285"
    },
    {
      "title": "Maison Martin Margiela Archive 0/010 (1989–2009)",
      "store": "Donlon Books",
      "city": "런던",
      "section": "아트·사진",
      "author": "Donlon Books",
      "store_cover": "https://cdn.shopify.com/s/files/1/0221/7340/files/Screenshot2026-04-21at13.18.42.png?v=1776775645",
      "store_link": "https://donlonbooks.com/products/maison-martin-margiela-archive-0-010-1989-2009",
      "published_at": "2026-04-21T13:35:37+01:00",
      "cover": "https://cdn.shopify.com/s/files/1/0221/7340/files/Screenshot2026-04-21at13.18.42.png?v=1776775645"
    },
    {
      "title": "Avantpet Cooling Mat: Pug",
      "store": "Magma Books",
      "city": "런던",
      "section": "디자인·아트",
      "author": "Different than Magma",
      "store_cover": "https://cdn.shopify.com/s/files/1/0285/4760/products/2020-10-29_11-29-24.jpg?v=1603971516",
      "store_link": "https://magmabooks.com/products/avantpet-cooling-mat-pug",
      "published_at": "2026-06-22T13:30:53+01:00",
      "cover": "https://cdn.shopify.com/s/files/1/0285/4760/products/2020-10-29_11-29-24.jpg?v=1603971516"
    },
    {
      "title": "True Love #2",
      "store": "Magma Books",
      "city": "런던",
      "section": "디자인·아트",
      "author": "Different than Magma",
      "store_cover": "https://cdn.shopify.com/s/files/1/0285/4760/files/Screenshot2026-06-22132434.png?v=1782131178",
      "store_link": "https://magmabooks.com/products/true-love-2",
      "published_at": "2026-06-22T13:26:32+01:00",
      "cover": "https://cdn.shopify.com/s/files/1/0285/4760/files/Screenshot2026-06-22132434.png?v=1782131178"
    },
    {
      "title": "Fay #2",
      "store": "Magma Books",
      "city": "런던",
      "section": "디자인·아트",
      "author": "Different than Magma",
      "store_cover": "https://cdn.shopify.com/s/files/1/0285/4760/files/Screenshot2026-06-22131633.png?v=1782130666",
      "store_link": "https://magmabooks.com/products/fay-2",
      "published_at": "2026-06-22T13:18:07+01:00",
      "cover": "https://cdn.shopify.com/s/files/1/0285/4760/files/Screenshot2026-06-22131633.png?v=1782130666"
    },
    {
      "title": "EATEN #26",
      "store": "Magma Books",
      "city": "런던",
      "section": "디자인·아트",
      "author": "Different than Magma",
      "store_cover": "https://cdn.shopify.com/s/files/1/0285/4760/files/Screenshot2026-06-22131307.png?v=1782130515",
      "store_link": "https://magmabooks.com/products/eaten-26",
      "published_at": "2026-06-22T13:15:27+01:00",
      "cover": "https://cdn.shopify.com/s/files/1/0285/4760/files/Screenshot2026-06-22131307.png?v=1782130515"
    },
    {
      "title": "Record Culture #11",
      "store": "Magma Books",
      "city": "런던",
      "section": "디자인·아트",
      "author": "Different than Magma",
      "store_cover": "https://cdn.shopify.com/s/files/1/0285/4760/files/be797745-cb6c-737a-ed77-ecf1b0817b7c.jpg?v=1780660003",
      "store_link": "https://magmabooks.com/products/record-culture-11",
      "published_at": "2026-06-22T13:09:08+01:00",
      "cover": "https://cdn.shopify.com/s/files/1/0285/4760/files/be797745-cb6c-737a-ed77-ecf1b0817b7c.jpg?v=1780660003"
    },
    {
      "title": "Boys Boys Boys! #11",
      "store": "Magma Books",
      "city": "런던",
      "section": "디자인·아트",
      "author": "Different than Magma",
      "store_cover": "https://cdn.shopify.com/s/files/1/0285/4760/files/Cover_Web.webp?v=1782061077",
      "store_link": "https://magmabooks.com/products/boys-boys-boys-12",
      "published_at": "2026-06-21T18:00:44+01:00",
      "cover": "https://cdn.shopify.com/s/files/1/0285/4760/files/Cover_Web.webp?v=1782061077"
    },
    {
      "title": "Serviette #8",
      "store": "Magma Books",
      "city": "런던",
      "section": "디자인·아트",
      "author": "Different than Magma",
      "store_cover": "https://cdn.shopify.com/s/files/1/0285/4760/files/serviette.webp?v=1782060391",
      "store_link": "https://magmabooks.com/products/serviette-8",
      "published_at": "2026-06-21T17:48:41+01:00",
      "cover": "https://cdn.shopify.com/s/files/1/0285/4760/files/serviette.webp?v=1782060391"
    },
    {
      "title": "Flavours & Friends: Piccolo Edition",
      "store": "Magma Books",
      "city": "런던",
      "section": "디자인·아트",
      "author": "Different than Magma",
      "store_cover": "https://cdn.shopify.com/s/files/1/0285/4760/files/Screenshot2026-06-20at17-08-13TDDBOOK-FLAVOURS_FRIENDSTDDshop.png?v=1781971718",
      "store_link": "https://magmabooks.com/products/bar-brutal-a-cookbook-of-revelations-copy",
      "published_at": "2026-06-20T17:08:52+01:00",
      "cover": "https://cdn.shopify.com/s/files/1/0285/4760/files/Screenshot2026-06-20at17-08-13TDDBOOK-FLAVOURS_FRIENDSTDDshop.png?v=1781971718"
    },
    {
      "title": "On the Rag #3: Special London Edition",
      "store": "Magma Books",
      "city": "런던",
      "section": "디자인·아트",
      "author": "Different than Magma",
      "store_cover": "https://cdn.shopify.com/s/files/1/0285/4760/files/Screenshot2026-06-20at16-56-37OnTheRag_3-LondonEdition_UNITOM.png?v=1781971136",
      "store_link": "https://magmabooks.com/products/useless-5-copy",
      "published_at": "2026-06-20T16:59:51+01:00",
      "cover": "https://cdn.shopify.com/s/files/1/0285/4760/files/Screenshot2026-06-20at16-56-37OnTheRag_3-LondonEdition_UNITOM.png?v=1781971136"
    },
    {
      "title": "BILL #6",
      "store": "Magma Books",
      "city": "런던",
      "section": "디자인·아트",
      "author": "Different than Magma",
      "store_cover": "https://cdn.shopify.com/s/files/1/0285/4760/files/Screenshot2026-06-20at16-46-35BILLissue6-GoogleSearch.png?v=1781970416",
      "store_link": "https://magmabooks.com/products/bill-5-copy",
      "published_at": "2026-06-20T16:47:17+01:00",
      "cover": "https://cdn.shopify.com/s/files/1/0285/4760/files/Screenshot2026-06-20at16-46-35BILLissue6-GoogleSearch.png?v=1781970416"
    },
    {
      "title": "Endless Magazine #5",
      "store": "Magma Books",
      "city": "런던",
      "section": "디자인·아트",
      "author": "Different than Magma",
      "store_cover": "https://cdn.shopify.com/s/files/1/0285/4760/files/Screenshot2026-06-20at16-32-03endlessmagazineIV-GoogleSearch.png?v=1781969546",
      "store_link": "https://magmabooks.com/products/endless-magazine-3-copy",
      "published_at": "2026-06-20T16:39:21+01:00",
      "cover": "https://cdn.shopify.com/s/files/1/0285/4760/files/Screenshot2026-06-20at16-32-03endlessmagazineIV-GoogleSearch.png?v=1781969546"
    },
    {
      "title": "Apartamento #37",
      "store": "Magma Books",
      "city": "런던",
      "section": "디자인·아트",
      "author": "Different than Magma",
      "store_cover": "https://cdn.shopify.com/s/files/1/0285/4760/files/Screenshot2026-06-19173103.png?v=1781886963",
      "store_link": "https://magmabooks.com/products/apartamento-35-copy-2",
      "published_at": "2026-06-19T17:37:16+01:00",
      "cover": "https://cdn.shopify.com/s/files/1/0285/4760/files/Screenshot2026-06-19173103.png?v=1781886963"
    },
    {
      "title": "A Magazine: Curated by Hores Serie (for Nike) #7",
      "store": "Magma Books",
      "city": "런던",
      "section": "디자인·아트",
      "author": "Different than Magma",
      "store_cover": "https://cdn.shopify.com/s/files/1/0285/4760/files/Screenshot2026-06-19172213.png?v=1781886526",
      "store_link": "https://magmabooks.com/products/a-magazine-curated-by-cecile-bahnsen-copy",
      "published_at": "2026-06-19T17:30:12+01:00",
      "cover": "https://cdn.shopify.com/s/files/1/0285/4760/files/Screenshot2026-06-19172213.png?v=1781886526"
    },
    {
      "title": "THE ECHO: How to Design Brands That Move Culture",
      "store": "Magma Books",
      "city": "런던",
      "section": "디자인·아트",
      "author": "Different than Magma",
      "store_cover": "https://cdn.shopify.com/s/files/1/0285/4760/files/Screenshot2026-06-19171247.png?v=1781885813",
      "store_link": "https://magmabooks.com/products/what-design-can-t-do-copy",
      "published_at": "2026-06-19T17:18:28+01:00",
      "cover": "https://cdn.shopify.com/s/files/1/0285/4760/files/Screenshot2026-06-19171247.png?v=1781885813"
    },
    {
      "title": "Design360° no.112 – What Are the Most Beautiful Books?",
      "store": "Magma Books",
      "city": "런던",
      "section": "디자인·아트",
      "author": "Different than Magma",
      "store_cover": "https://cdn.shopify.com/s/files/1/0285/4760/files/Screenshot2026-06-19123938.png?v=1781870995",
      "store_link": "https://magmabooks.com/products/reset-1-copy",
      "published_at": "2026-06-19T13:10:52+01:00",
      "cover": "https://cdn.shopify.com/s/files/1/0285/4760/files/Screenshot2026-06-19123938.png?v=1781870995"
    },
    {
      "title": "Reset #1",
      "store": "Magma Books",
      "city": "런던",
      "section": "디자인·아트",
      "author": "Different than Magma",
      "store_cover": "https://cdn.shopify.com/s/files/1/0285/4760/files/Screenshot2026-06-01at17-49-33reset-magazine-1_1600x1600.jpg_JPEGImage1600x1333pixels_Scaled_66.png?v=1780332638",
      "store_link": "https://magmabooks.com/products/reset-1",
      "published_at": "2026-06-19T13:08:52+01:00",
      "cover": "https://cdn.shopify.com/s/files/1/0285/4760/files/Screenshot2026-06-01at17-49-33reset-magazine-1_1600x1600.jpg_JPEGImage1600x1333pixels_Scaled_66.png?v=1780332638"
    },
    {
      "title": "Core Corea – Issue 2",
      "store": "Magma Books",
      "city": "런던",
      "section": "디자인·아트",
      "author": "Different than Magma",
      "store_cover": "https://cdn.shopify.com/s/files/1/0285/4760/files/Screenshot2026-06-19123728.png?v=1781870598",
      "store_link": "https://magmabooks.com/products/breakout-2-100-posters-copy",
      "published_at": "2026-06-19T13:03:51+01:00",
      "cover": "https://cdn.shopify.com/s/files/1/0285/4760/files/Screenshot2026-06-19123728.png?v=1781870598"
    },
    {
      "title": "Breakout #2 – 100 Posters",
      "store": "Magma Books",
      "city": "런던",
      "section": "디자인·아트",
      "author": "Different than Magma",
      "store_cover": "https://cdn.shopify.com/s/files/1/0285/4760/files/Screenshot2026-06-19123449.png?v=1781870379",
      "store_link": "https://magmabooks.com/products/slanted-magazine-47-digital-tools-copy",
      "published_at": "2026-06-19T13:01:43+01:00",
      "cover": "https://cdn.shopify.com/s/files/1/0285/4760/files/Screenshot2026-06-19123449.png?v=1781870379"
    },
    {
      "title": "Slanted Magazine #47 – Digital Tools",
      "store": "Magma Books",
      "city": "런던",
      "section": "디자인·아트",
      "author": "Different than Magma",
      "store_cover": "https://cdn.shopify.com/s/files/1/0285/4760/files/Screenshot2026-06-19123206.png?v=1781870155",
      "store_link": "https://magmabooks.com/products/slanted-46-cairo-copy",
      "published_at": "2026-06-19T12:58:06+01:00",
      "cover": "https://cdn.shopify.com/s/files/1/0285/4760/files/Screenshot2026-06-19123206.png?v=1781870155"
    },
    {
      "title": "Lionel Wendt",
      "store": "Magma Books",
      "city": "런던",
      "section": "디자인·아트",
      "author": "Different than Magma",
      "store_cover": "https://cdn.shopify.com/s/files/1/0285/4760/files/Screenshot2026-06-19122813.png?v=1781869898",
      "store_link": "https://magmabooks.com/products/inframundi-copy",
      "published_at": "2026-06-19T12:53:58+01:00",
      "cover": "https://cdn.shopify.com/s/files/1/0285/4760/files/Screenshot2026-06-19122813.png?v=1781869898"
    },
    {
      "title": "Mast Books Tote Bag",
      "store": "Mast Books",
      "city": "뉴욕",
      "section": "아트·희귀본",
      "author": "Mast Books",
      "store_cover": "https://cdn.shopify.com/s/files/1/0290/3562/6574/products/tote-1-200dpi.jpg?v=1623468379",
      "store_link": "https://mastbooks.com/products/tote-bag",
      "published_at": "2025-12-22T14:35:45-05:00",
      "cover": "https://cdn.shopify.com/s/files/1/0290/3562/6574/products/tote-1-200dpi.jpg?v=1623468379"
    },
    {
      "title": "A Day in the Life of Rowland S Howard",
      "store": "Mast Books",
      "city": "뉴욕",
      "section": "아트·희귀본",
      "author": "Peter Milne",
      "store_cover": "https://cdn.shopify.com/s/files/1/0290/3562/6574/products/Milne_Day_Front.jpg?v=1638834396",
      "store_link": "https://mastbooks.com/products/a-day-in-the-life-of-rowland-s-howard",
      "published_at": "2025-07-11T16:26:32-04:00",
      "cover": "https://cdn.shopify.com/s/files/1/0290/3562/6574/products/Milne_Day_Front.jpg?v=1638834396"
    },
    {
      "title": "The Great Gatsby",
      "store": "Mast Books",
      "city": "뉴욕",
      "section": "아트·희귀본",
      "author": "F. Scott Fitzgerald",
      "store_cover": "https://cdn.shopify.com/s/files/1/0290/3562/6574/files/MB_FITZGERALD_GATSBY_01-1.jpg?v=1750977787",
      "store_link": "https://mastbooks.com/products/the-great-gatsby",
      "published_at": "2025-06-26T18:48:15-04:00",
      "cover": "https://cdn.shopify.com/s/files/1/0290/3562/6574/files/MB_FITZGERALD_GATSBY_01-1.jpg?v=1750977787"
    },
    {
      "title": "Hamptons Guide [1968]",
      "store": "Mast Books",
      "city": "뉴욕",
      "section": "아트·희귀본",
      "author": "Dan Rattiner",
      "store_cover": "https://cdn.shopify.com/s/files/1/0290/3562/6574/files/MB_HAMPTONS_GUIDE_01.jpg?v=1750877424",
      "store_link": "https://mastbooks.com/products/hamptons-guide-1968",
      "published_at": "2025-06-25T14:50:31-04:00",
      "cover": "https://cdn.shopify.com/s/files/1/0290/3562/6574/files/MB_HAMPTONS_GUIDE_01.jpg?v=1750877424"
    },
    {
      "title": "AREA 1983 -1987",
      "store": "Mast Books",
      "city": "뉴욕",
      "section": "아트·희귀본",
      "author": "Eric Goode and Jennifer Goode",
      "store_cover": "https://cdn.shopify.com/s/files/1/0290/3562/6574/files/MB_GOODE_AREA_01.jpg?v=1748281099",
      "store_link": "https://mastbooks.com/products/area-1983-1987",
      "published_at": "2025-05-26T13:35:30-04:00",
      "cover": "https://cdn.shopify.com/s/files/1/0290/3562/6574/files/MB_GOODE_AREA_01.jpg?v=1748281099"
    },
    {
      "title": "Of & About Posters : The Lawrence Weiner Poster Archive (1965-2021) at the Vancouver Art Gallery",
      "store": "Mast Books",
      "city": "뉴욕",
      "section": "아트·희귀본",
      "author": "Lawrence Weiner",
      "store_cover": "https://cdn.shopify.com/s/files/1/0290/3562/6574/files/MB_WEINER_POSTERS_01.jpg?v=1747426993",
      "store_link": "https://mastbooks.com/products/of-about-posters-the-lawrence-weiner-poster-archive-1965-2021-at-the-vancouver-art-gallery",
      "published_at": "2025-05-16T16:23:21-04:00",
      "cover": "https://cdn.shopify.com/s/files/1/0290/3562/6574/files/MB_WEINER_POSTERS_01.jpg?v=1747426993"
    },
    {
      "title": "Dawn in Spring",
      "store": "Mast Books",
      "city": "뉴욕",
      "section": "아트·희귀본",
      "author": "Asako Narahashi",
      "store_cover": "https://cdn.shopify.com/s/files/1/0290/3562/6574/files/MB_NARAHASHI_DAWN_01.jpg?v=1747426597",
      "store_link": "https://mastbooks.com/products/dawn-in-spring",
      "published_at": "2025-05-16T16:17:28-04:00",
      "cover": "https://cdn.shopify.com/s/files/1/0290/3562/6574/files/MB_NARAHASHI_DAWN_01.jpg?v=1747426597"
    },
    {
      "title": "K",
      "store": "Mast Books",
      "city": "뉴욕",
      "section": "아트·희귀본",
      "author": "Daido Moriyama",
      "store_cover": "https://cdn.shopify.com/s/files/1/0290/3562/6574/files/MB_MORIYAMA_K_01.jpg?v=1747425964",
      "store_link": "https://mastbooks.com/products/k",
      "published_at": "2025-05-16T16:06:12-04:00",
      "cover": "https://cdn.shopify.com/s/files/1/0290/3562/6574/files/MB_MORIYAMA_K_01.jpg?v=1747425964"
    },
    {
      "title": "Farewell Photography",
      "store": "Mast Books",
      "city": "뉴욕",
      "section": "아트·희귀본",
      "author": "Daido Moriyama",
      "store_cover": "https://cdn.shopify.com/s/files/1/0290/3562/6574/files/MB_MORIYAMA_FAREWELL_01.jpg?v=1747425462",
      "store_link": "https://mastbooks.com/products/farewell-photography",
      "published_at": "2025-05-16T15:58:04-04:00",
      "cover": "https://cdn.shopify.com/s/files/1/0290/3562/6574/files/MB_MORIYAMA_FAREWELL_01.jpg?v=1747425462"
    },
    {
      "title": "Dog and Mesh Tights",
      "store": "Mast Books",
      "city": "뉴욕",
      "section": "아트·희귀본",
      "author": "Daido Moriyama",
      "store_cover": "https://cdn.shopify.com/s/files/1/0290/3562/6574/files/MB_MORIYAMA_DOG_MESH_01.jpg?v=1747424664",
      "store_link": "https://mastbooks.com/products/dog-and-mesh-tights",
      "published_at": "2025-05-16T15:44:50-04:00",
      "cover": "https://cdn.shopify.com/s/files/1/0290/3562/6574/files/MB_MORIYAMA_DOG_MESH_01.jpg?v=1747424664"
    },
    {
      "title": "COMME DES GARÇONS PARFUMS 1994-2025",
      "store": "Mast Books",
      "city": "뉴욕",
      "section": "아트·희귀본",
      "author": "Dino Simonett (ed.)",
      "store_cover": "https://cdn.shopify.com/s/files/1/0290/3562/6574/files/MB_COMME_PARFUMS_01.jpg?v=1747424368",
      "store_link": "https://mastbooks.com/products/comme-des-garcons-parfums-1994-2025",
      "published_at": "2025-05-16T15:39:41-04:00",
      "cover": "https://cdn.shopify.com/s/files/1/0290/3562/6574/files/MB_COMME_PARFUMS_01.jpg?v=1747424368"
    },
    {
      "title": "The Secret History Of Kate Bush",
      "store": "Mast Books",
      "city": "뉴욕",
      "section": "아트·희귀본",
      "author": "Fred Vermorel",
      "store_cover": "https://cdn.shopify.com/s/files/1/0290/3562/6574/files/MB_BUSH_SECRET_HISTORY_01.jpg?v=1747424101",
      "store_link": "https://mastbooks.com/products/the-secret-history-of-kate-bush",
      "published_at": "2025-05-16T15:37:19-04:00",
      "cover": "https://cdn.shopify.com/s/files/1/0290/3562/6574/files/MB_BUSH_SECRET_HISTORY_01.jpg?v=1747424101"
    },
    {
      "title": "Butt Magazine Number Six [#6]: Fagazine, Spring 2003",
      "store": "Mast Books",
      "city": "뉴욕",
      "section": "아트·희귀본",
      "author": "Jonkers, Gert and Jop van Bennekom",
      "store_cover": "https://cdn.shopify.com/s/files/1/0290/3562/6574/files/MB_BUTT_06_01.jpg?v=1745344642",
      "store_link": "https://mastbooks.com/products/butt-number-six-6-fagazine-spring-2003-copy",
      "published_at": "2025-04-22T14:06:13-04:00",
      "cover": "https://cdn.shopify.com/s/files/1/0290/3562/6574/files/MB_BUTT_06_01.jpg?v=1745344642"
    },
    {
      "title": "Butt Magazine #26: The Homosexualist Quarterly, Springtime 2009",
      "store": "Mast Books",
      "city": "뉴욕",
      "section": "아트·희귀본",
      "author": "Jonkers, Gert and Jop van Bennekom",
      "store_cover": "https://cdn.shopify.com/s/files/1/0290/3562/6574/files/MB_BUTT_26_01.jpg?v=1745345114",
      "store_link": "https://mastbooks.com/products/butt-magazine-25-the-homo-quarterly-winter-2008-09-copy",
      "published_at": "2025-04-22T14:05:44-04:00",
      "cover": "https://cdn.shopify.com/s/files/1/0290/3562/6574/files/MB_BUTT_26_01.jpg?v=1745345114"
    },
    {
      "title": "Butt Magazine #25: The Homo Quarterly, Winter 2008/09",
      "store": "Mast Books",
      "city": "뉴욕",
      "section": "아트·희귀본",
      "author": "Jonkers, Gert and Jop van Bennekom",
      "store_cover": "https://cdn.shopify.com/s/files/1/0290/3562/6574/files/MB_BUTT_25_01.jpg?v=1745345013",
      "store_link": "https://mastbooks.com/products/butt-magazine-17-amazing-magazine-for-homosexuals-autumn-2006-copy",
      "published_at": "2025-04-22T14:04:11-04:00",
      "cover": "https://cdn.shopify.com/s/files/1/0290/3562/6574/files/MB_BUTT_25_01.jpg?v=1745345013"
    },
    {
      "title": "Butt Magazine #17: Amazing Magazine For Homosexuals, Autumn 2006",
      "store": "Mast Books",
      "city": "뉴욕",
      "section": "아트·희귀본",
      "author": "Jonkers, Gert and Jop van Bennekom",
      "store_cover": "https://cdn.shopify.com/s/files/1/0290/3562/6574/files/MB_BUTT_17_01.jpg?v=1745344870",
      "store_link": "https://mastbooks.com/products/butt-number-six-6-fagazine-spring-2003-copy-copy",
      "published_at": "2025-04-22T14:01:27-04:00",
      "cover": "https://cdn.shopify.com/s/files/1/0290/3562/6574/files/MB_BUTT_17_01.jpg?v=1745344870"
    },
    {
      "title": "Butt Magazine Number Five [#5]: Autumn 2002",
      "store": "Mast Books",
      "city": "뉴욕",
      "section": "아트·희귀본",
      "author": "Jonkers, Gert and Jop van Bennekom",
      "store_cover": "https://cdn.shopify.com/s/files/1/0290/3562/6574/files/MB_BUTT_05_01.jpg?v=1745344760",
      "store_link": "https://mastbooks.com/products/butt-number-four-4-fag-mag-summer-2002-copy",
      "published_at": "2025-04-22T13:57:44-04:00",
      "cover": "https://cdn.shopify.com/s/files/1/0290/3562/6574/files/MB_BUTT_05_01.jpg?v=1745344760"
    },
    {
      "title": "Butt Magazine Number Four [#4]: Fag Mag, Summer 2002",
      "store": "Mast Books",
      "city": "뉴욕",
      "section": "아트·희귀본",
      "author": "Jonkers, Gert and Jop van Bennekom",
      "store_cover": "https://cdn.shopify.com/s/files/1/0290/3562/6574/files/MB_BUTT_04_01.jpg?v=1745344135",
      "store_link": "https://mastbooks.com/products/butt-number-four-4-fag-mag-summer-2002",
      "published_at": "2025-04-22T13:53:55-04:00",
      "cover": "https://cdn.shopify.com/s/files/1/0290/3562/6574/files/MB_BUTT_04_01.jpg?v=1745344135"
    },
    {
      "title": "Can Lis",
      "store": "Mast Books",
      "city": "뉴욕",
      "section": "아트·희귀본",
      "author": "Jørn Utzon",
      "store_cover": "https://cdn.shopify.com/s/files/1/0290/3562/6574/files/MB_UTZON_WATSON_O1.jpg?v=1744486960",
      "store_link": "https://mastbooks.com/products/can-lis",
      "published_at": "2025-04-12T15:30:10-04:00",
      "cover": "https://cdn.shopify.com/s/files/1/0290/3562/6574/files/MB_UTZON_WATSON_O1.jpg?v=1744486960"
    },
    {
      "title": "Revue Faire 49: We Are Ships at Sea, Not Ducks On a Pond",
      "store": "Mast Books",
      "city": "뉴욕",
      "section": "아트·희귀본",
      "author": "Lawrence Weiner",
      "store_cover": "https://cdn.shopify.com/s/files/1/0290/3562/6574/files/MB_WEINER_WE_ARE_SHIPS_01.jpg?v=1744483758",
      "store_link": "https://mastbooks.com/products/revue-faire-49-we-are-ships-at-sea-not-ducks-on-a-pond",
      "published_at": "2025-04-12T14:52:12-04:00",
      "cover": "https://cdn.shopify.com/s/files/1/0290/3562/6574/files/MB_WEINER_WE_ARE_SHIPS_01.jpg?v=1744483758"
    },
    {
      "title": "Beyond Color: White Interiors from Simple to Sublime",
      "store": "Phaidon",
      "city": "출판사",
      "section": "아트·디자인",
      "author": "The Monacelli Press",
      "store_cover": "https://cdn.shopify.com/s/files/1/0711/5292/6820/files/M-white-rooms-ae-3774-3d-standing-front-3000.jpg?v=1781807866",
      "store_link": "https://www.phaidon.com/products/beyond-color-white-interiors-from-simple-to-sublime",
      "published_at": "2026-06-22T23:01:16+01:00",
      "cover": "https://cdn.shopify.com/s/files/1/0711/5292/6820/files/M-white-rooms-ae-3774-3d-standing-front-3000.jpg?v=1781807866"
    },
    {
      "title": "Mathieu Lehanneur",
      "store": "Phaidon",
      "city": "출판사",
      "section": "아트·디자인",
      "author": "Phaidon Press",
      "store_cover": "https://cdn.shopify.com/s/files/1/0711/5292/6820/files/mathieu-lehanneur-en-9229-3d-standing-front-3000.jpg?v=1781845348",
      "store_link": "https://www.phaidon.com/products/mathieu-lehanneur",
      "published_at": "2026-06-22T22:28:49+01:00",
      "cover": "https://cdn.shopify.com/s/files/1/0711/5292/6820/files/mathieu-lehanneur-en-9229-3d-standing-front-3000.jpg?v=1781845348"
    },
    {
      "title": "Once Around the Sun: Seasonal Rituals, Food, and Stories from a House Upstate",
      "store": "Phaidon",
      "city": "출판사",
      "section": "아트·디자인",
      "author": "The Monacelli Press",
      "store_cover": "https://cdn.shopify.com/s/files/1/0711/5292/6820/files/M-once-around-the-sun-en-7443-3d-standing-front-3000.jpg?v=1780430900",
      "store_link": "https://www.phaidon.com/products/once-around-the-sun-seasonal-rituals-food-and-stories-from-a-house-upstate",
      "published_at": "2026-06-22T21:31:22+01:00",
      "cover": "https://cdn.shopify.com/s/files/1/0711/5292/6820/files/M-once-around-the-sun-en-7443-3d-standing-front-3000.jpg?v=1780430900"
    },
    {
      "title": "The Festive Baker: A Cookbook - Baking for celebrations and special occasions around the world",
      "store": "Phaidon",
      "city": "출판사",
      "section": "아트·디자인",
      "author": "Phaidon Press",
      "store_cover": "https://cdn.shopify.com/s/files/1/0711/5292/6820/files/the-festive-baker-en-9261-3d-standing-front-3000.jpg?v=1780331191",
      "store_link": "https://www.phaidon.com/products/the-festive-baker-a-cookbook-baking-for-celebrations-and-special-occasions-around-the-world",
      "published_at": "2026-06-22T19:55:02+01:00",
      "cover": "https://cdn.shopify.com/s/files/1/0711/5292/6820/files/the-festive-baker-en-9261-3d-standing-front-3000.jpg?v=1780331191"
    },
    {
      "title": "Vegan Vegan!",
      "store": "Phaidon",
      "city": "출판사",
      "section": "아트·디자인",
      "author": "Phaidon Press",
      "store_cover": "https://cdn.shopify.com/s/files/1/0711/5292/6820/files/vegan-vegan-en-9262-3d-standing-front-3000.jpg?v=1779978317",
      "store_link": "https://www.phaidon.com/products/vegan-vegan",
      "published_at": "2026-06-22T14:28:03+01:00",
      "cover": "https://cdn.shopify.com/s/files/1/0711/5292/6820/files/vegan-vegan-en-9262-3d-standing-front-3000.jpg?v=1779978317"
    },
    {
      "title": "Tuscany",
      "store": "Phaidon",
      "city": "출판사",
      "section": "아트·디자인",
      "author": "Phaidon Press",
      "store_cover": "https://cdn.shopify.com/s/files/1/0711/5292/6820/files/tuscany-2026-en-9245-3d-standing-front-3000.jpg?v=1779978518",
      "store_link": "https://www.phaidon.com/products/tuscany",
      "published_at": "2026-06-22T14:27:34+01:00",
      "cover": "https://cdn.shopify.com/s/files/1/0711/5292/6820/files/tuscany-2026-en-9245-3d-standing-front-3000.jpg?v=1779978518"
    },
    {
      "title": "Sicily (2026)",
      "store": "Phaidon",
      "city": "출판사",
      "section": "아트·디자인",
      "author": "Phaidon Press",
      "store_cover": "https://cdn.shopify.com/s/files/1/0711/5292/6820/files/sicily-2026-en-9246-3d-standing-front-3000.jpg?v=1779978806",
      "store_link": "https://www.phaidon.com/products/sicily-2026",
      "published_at": "2026-06-22T14:26:39+01:00",
      "cover": "https://cdn.shopify.com/s/files/1/0711/5292/6820/files/sicily-2026-en-9246-3d-standing-front-3000.jpg?v=1779978806"
    },
    {
      "title": "Into the Garden: Private Sanctuaries Around the World",
      "store": "Phaidon",
      "city": "출판사",
      "section": "아트·디자인",
      "author": "Phaidon Press",
      "store_cover": "https://cdn.shopify.com/s/files/1/0711/5292/6820/files/into-the-garden-en-9311-3d-standing-front-3000.jpg?v=1780331166",
      "store_link": "https://www.phaidon.com/products/into-the-garden-private-sanctuaries-around-the-world",
      "published_at": "2026-06-22T13:44:12+01:00",
      "cover": "https://cdn.shopify.com/s/files/1/0711/5292/6820/files/into-the-garden-en-9311-3d-standing-front-3000.jpg?v=1780331166"
    },
    {
      "title": "Boundless Spirit: Iranian Women Artists",
      "store": "Phaidon",
      "city": "출판사",
      "section": "아트·디자인",
      "author": "The Monacelli Press",
      "store_cover": "https://cdn.shopify.com/s/files/1/0711/5292/6820/files/M-iranian-women-artists-ae-3750-3d-standing-front-3000.jpg?v=1780330517",
      "store_link": "https://www.phaidon.com/products/boundless-spirit-iranian-women-artists",
      "published_at": "2026-06-22T13:42:55+01:00",
      "cover": "https://cdn.shopify.com/s/files/1/0711/5292/6820/files/M-iranian-women-artists-ae-3750-3d-standing-front-3000.jpg?v=1780330517"
    },
    {
      "title": "Architects' Houses",
      "store": "Phaidon",
      "city": "출판사",
      "section": "아트·디자인",
      "author": "Phaidon Press",
      "store_cover": "https://cdn.shopify.com/s/files/1/0711/5292/6820/files/architects-houses-en-9226-3d-standing-front-3000.jpg?v=1780330331",
      "store_link": "https://www.phaidon.com/products/architects-houses",
      "published_at": "2026-06-22T13:42:01+01:00",
      "cover": "https://cdn.shopify.com/s/files/1/0711/5292/6820/files/architects-houses-en-9226-3d-standing-front-3000.jpg?v=1780330331"
    },
    {
      "title": "Spiced: Recipes Celebrating Spices from Around the World",
      "store": "Phaidon",
      "city": "출판사",
      "section": "아트·디자인",
      "author": "Phaidon Press",
      "store_cover": "https://cdn.shopify.com/s/files/1/0711/5292/6820/files/spiced-en-9265-3d-standing-front-3000.jpg?v=1780330979",
      "store_link": "https://www.phaidon.com/products/spiced-recipes-celebrating-spices-from-around-the-world",
      "published_at": "2026-06-22T13:38:29+01:00",
      "cover": "https://cdn.shopify.com/s/files/1/0711/5292/6820/files/spiced-en-9265-3d-standing-front-3000.jpg?v=1780330979"
    },
    {
      "title": "Brilliant: Unexpected Art from Everywhere",
      "store": "Phaidon",
      "city": "출판사",
      "section": "아트·디자인",
      "author": "The Monacelli Press",
      "store_cover": "https://cdn.shopify.com/s/files/1/0711/5292/6820/files/M-brilliant-ae-3757-3d-standing-front-3000.jpg?v=1780330497",
      "store_link": "https://www.phaidon.com/products/brilliant-unexpected-art-from-everywhere",
      "published_at": "2026-06-18T20:29:32+01:00",
      "cover": "https://cdn.shopify.com/s/files/1/0711/5292/6820/files/M-brilliant-ae-3757-3d-standing-front-3000.jpg?v=1780330497"
    },
    {
      "title": "Us Is More: INC Architecture & Design",
      "store": "Phaidon",
      "city": "출판사",
      "section": "아트·디자인",
      "author": "The Monacelli Press",
      "store_cover": "https://cdn.shopify.com/s/files/1/0711/5292/6820/files/M-us-is-more-ae-3749-3d-standing-front-3000.jpg?v=1779978462",
      "store_link": "https://www.phaidon.com/products/us-is-more-inc-architecture-design",
      "published_at": "2026-06-18T20:25:13+01:00",
      "cover": "https://cdn.shopify.com/s/files/1/0711/5292/6820/files/M-us-is-more-ae-3749-3d-standing-front-3000.jpg?v=1779978462"
    },
    {
      "title": "Time & Place: The Homes of Richard Beard Architects",
      "store": "Phaidon",
      "city": "출판사",
      "section": "아트·디자인",
      "author": "The Monacelli Press",
      "store_cover": "https://cdn.shopify.com/s/files/1/0711/5292/6820/files/M-richard-beard-architects-ae-3767-3d-standing-front-3000.jpg?v=1780330546",
      "store_link": "https://www.phaidon.com/products/time-place-the-homes-of-richard-beard-architects",
      "published_at": "2026-06-18T20:23:26+01:00",
      "cover": "https://cdn.shopify.com/s/files/1/0711/5292/6820/files/M-richard-beard-architects-ae-3767-3d-standing-front-3000.jpg?v=1780330546"
    },
    {
      "title": "Mory Sacko: A Cook's Journey",
      "store": "Phaidon",
      "city": "출판사",
      "section": "아트·디자인",
      "author": "Phaidon Press",
      "store_cover": "https://cdn.shopify.com/s/files/1/0711/5292/6820/files/mory-sacko-en-9044-3d-standing-front-3000.jpg?v=1780330407",
      "store_link": "https://www.phaidon.com/products/mory-sacko-a-cooks-journey",
      "published_at": "2026-06-18T20:07:32+01:00",
      "cover": "https://cdn.shopify.com/s/files/1/0711/5292/6820/files/mory-sacko-en-9044-3d-standing-front-3000.jpg?v=1780330407"
    },
    {
      "title": "At Home in Nature: American Country Interiors",
      "store": "Phaidon",
      "city": "출판사",
      "section": "아트·디자인",
      "author": "The Monacelli Press",
      "store_cover": "https://cdn.shopify.com/s/files/1/0711/5292/6820/files/M-at-home-in-nature-ae-3748-3d-standing-front-3000.jpg?v=1780430741",
      "store_link": "https://www.phaidon.com/products/at-home-in-nature-american-country-interiors",
      "published_at": "2026-06-18T20:05:24+01:00",
      "cover": "https://cdn.shopify.com/s/files/1/0711/5292/6820/files/M-at-home-in-nature-ae-3748-3d-standing-front-3000.jpg?v=1780430741"
    },
    {
      "title": "Eddie Martinez: 20 Years of Painting",
      "store": "Phaidon",
      "city": "출판사",
      "section": "아트·디자인",
      "author": "The Monacelli Press",
      "store_cover": "https://cdn.shopify.com/s/files/1/0711/5292/6820/files/M-eddie-martinez-ae-3751-3d-standing-front-3000.jpg?v=1780330673",
      "store_link": "https://www.phaidon.com/products/eddie-martinez-20-years-of-painting",
      "published_at": "2026-06-18T18:29:00+01:00",
      "cover": "https://cdn.shopify.com/s/files/1/0711/5292/6820/files/M-eddie-martinez-ae-3751-3d-standing-front-3000.jpg?v=1780330673"
    },
    {
      "title": "Animals of the Chinese Zodiac: Meet Your Match! An Illustrated Guide to the 12 Signs",
      "store": "Phaidon",
      "city": "출판사",
      "section": "아트·디자인",
      "author": "Phaidon Press",
      "store_cover": "https://cdn.shopify.com/s/files/1/0711/5292/6820/files/animals-of-the-chinese-zodiac-meet-your-match-en-9289-3d-standing-front-3000.jpg?v=1780331058",
      "store_link": "https://www.phaidon.com/products/animals-of-the-chinese-zodiac-meet-your-match-an-illustrated-guide-to-the-12-signs",
      "published_at": "2026-06-16T20:50:24+01:00",
      "cover": "https://cdn.shopify.com/s/files/1/0711/5292/6820/files/animals-of-the-chinese-zodiac-meet-your-match-en-9289-3d-standing-front-3000.jpg?v=1780331058"
    },
    {
      "title": "Animals of the Chinese Zodiac: Meet Your Match! : An Illustrated Guide to the 12 Signs",
      "store": "Phaidon",
      "city": "출판사",
      "section": "아트·디자인",
      "author": "Phaidon Press",
      "store_cover": "https://cdn.shopify.com/s/files/1/0711/5292/6820/files/animals-of-the-chinese-zodiac-meet-your-match-ae-9213-3d-standing-front-3000.jpg?v=1780401716",
      "store_link": "https://www.phaidon.com/products/animals-of-the-chinese-zodiac-meet-your-match-ae-an-illustrated-guide-to-the-12-signs",
      "published_at": "2026-06-16T20:32:28+01:00",
      "cover": "https://cdn.shopify.com/s/files/1/0711/5292/6820/files/animals-of-the-chinese-zodiac-meet-your-match-ae-9213-3d-standing-front-3000.jpg?v=1780401716"
    },
    {
      "title": "Another View: The Vibrant World of Contemporary Black Artists",
      "store": "Phaidon",
      "city": "출판사",
      "section": "아트·디자인",
      "author": "Phaidon Press",
      "store_cover": "https://cdn.shopify.com/s/files/1/0711/5292/6820/files/another-view-en-9022-3d-standing-front-3000.jpg?v=1780331308",
      "store_link": "https://www.phaidon.com/products/another-view-the-vibrant-world-of-contemporary-black-artists",
      "published_at": "2026-06-16T19:04:32+01:00",
      "cover": "https://cdn.shopify.com/s/files/1/0711/5292/6820/files/another-view-en-9022-3d-standing-front-3000.jpg?v=1780331308"
    },
    {
      "title": "The Jaguar Book: Collector's Edition",
      "store": "Gestalten",
      "city": "출판사",
      "section": "디자인",
      "author": "teNeues",
      "store_cover": "https://cdn.shopify.com/s/files/1/2717/4124/files/TheJaguarBook_front01.png?v=1760001104",
      "store_link": "https://shop.gestalten.com/products/the-jaguar-book-collectors-edition",
      "published_at": "2026-06-17T11:27:08+02:00",
      "cover": "https://cdn.shopify.com/s/files/1/2717/4124/files/TheJaguarBook_front01.png?v=1760001104"
    },
    {
      "title": "Basketball - Das ultimative Buch",
      "store": "Gestalten",
      "city": "출판사",
      "section": "디자인",
      "author": "teNeues",
      "store_cover": "https://cdn.shopify.com/s/files/1/2717/4124/files/BasektballDE_front.png?v=1760002489",
      "store_link": "https://shop.gestalten.com/products/basketball-das-ultimative-buch",
      "published_at": "2026-06-17T10:47:07+02:00",
      "cover": "https://cdn.shopify.com/s/files/1/2717/4124/files/BasektballDE_front.png?v=1760002489"
    },
    {
      "title": "Basketball - The Ultimate Book",
      "store": "Gestalten",
      "city": "출판사",
      "section": "디자인",
      "author": "teNeues",
      "store_cover": "https://cdn.shopify.com/s/files/1/2717/4124/files/BasketballEN_front.png?v=1760002402",
      "store_link": "https://shop.gestalten.com/products/basketball-the-ultimate-book",
      "published_at": "2026-06-17T10:47:04+02:00",
      "cover": "https://cdn.shopify.com/s/files/1/2717/4124/files/BasketballEN_front.png?v=1760002402"
    },
    {
      "title": "Fishing - The Ultimate Book",
      "store": "Gestalten",
      "city": "출판사",
      "section": "디자인",
      "author": "teNeues",
      "store_cover": "https://cdn.shopify.com/s/files/1/2717/4124/files/9783961716265_Fishing-The-Ultimate-Book_Cover-3D.png?v=1781622117",
      "store_link": "https://shop.gestalten.com/products/fishing-the-ultimate-book",
      "published_at": "2026-06-17T10:19:35+02:00",
      "cover": "https://cdn.shopify.com/s/files/1/2717/4124/files/9783961716265_Fishing-The-Ultimate-Book_Cover-3D.png?v=1781622117"
    },
    {
      "title": "The Stylish Life: Skiing",
      "store": "Gestalten",
      "city": "출판사",
      "section": "디자인",
      "author": "teNeues",
      "store_cover": "https://cdn.shopify.com/s/files/1/2717/4124/files/9783832732660_The-Stylish-Life-Skiing_Cover-front.png?v=1781532342",
      "store_link": "https://shop.gestalten.com/products/the-stylish-life-skiing",
      "published_at": "2026-06-17T10:16:34+02:00",
      "cover": "https://cdn.shopify.com/s/files/1/2717/4124/files/9783832732660_The-Stylish-Life-Skiing_Cover-front.png?v=1781532342"
    },
    {
      "title": "The Stylish Life: Cocktail Parties",
      "store": "Gestalten",
      "city": "출판사",
      "section": "디자인",
      "author": "teNeues",
      "store_cover": "https://cdn.shopify.com/s/files/1/2717/4124/files/9783961716661_The-Stylsih-Life-Cocktail-Parties_Cover-front.png?v=1781535488",
      "store_link": "https://shop.gestalten.com/products/the-stylish-life-cocktail-parties",
      "published_at": "2026-06-17T10:15:33+02:00",
      "cover": "https://cdn.shopify.com/s/files/1/2717/4124/files/9783961716661_The-Stylsih-Life-Cocktail-Parties_Cover-front.png?v=1781535488"
    },
    {
      "title": "The Stylish Life: Tennis",
      "store": "Gestalten",
      "city": "출판사",
      "section": "디자인",
      "author": "teNeues",
      "store_cover": "https://cdn.shopify.com/s/files/1/2717/4124/files/9783832732318_The-Stylish-Life-Tennis_Cover-front.png?v=1781538287",
      "store_link": "https://shop.gestalten.com/products/the-stylish-life-tennis",
      "published_at": "2026-06-17T10:14:08+02:00",
      "cover": "https://cdn.shopify.com/s/files/1/2717/4124/files/9783832732318_The-Stylish-Life-Tennis_Cover-front.png?v=1781538287"
    },
    {
      "title": "The Porsche Book",
      "store": "Gestalten",
      "city": "출판사",
      "section": "디자인",
      "author": "teNeues",
      "store_cover": "https://cdn.shopify.com/s/files/1/2717/4124/files/9783961716111_The-Porsche-Book_front.png?v=1741853143",
      "store_link": "https://shop.gestalten.com/products/teneues-the-porsche-book",
      "published_at": "2026-06-10T13:06:01+02:00",
      "cover": "https://cdn.shopify.com/s/files/1/2717/4124/files/9783961716111_The-Porsche-Book_front.png?v=1741853143"
    },
    {
      "title": "Metropolis",
      "store": "Gestalten",
      "city": "출판사",
      "section": "디자인",
      "author": "teNeues",
      "store_cover": "https://cdn.shopify.com/s/files/1/2717/4124/files/metropolis_01.png?v=1779480355",
      "store_link": "https://shop.gestalten.com/products/metropolis",
      "published_at": "2026-05-22T22:06:04+02:00",
      "cover": "https://cdn.shopify.com/s/files/1/2717/4124/files/metropolis_01.png?v=1779480355"
    },
    {
      "title": "The Lamborghini Book",
      "store": "Gestalten",
      "city": "출판사",
      "section": "디자인",
      "author": "teNeues",
      "store_cover": "https://cdn.shopify.com/s/files/1/2717/4124/files/9783961715114_The-Lamborghini-Book_Cover-front_dc67817c-dbe9-4c8b-8061-ff0bc59bfdb6.png?v=1779479166",
      "store_link": "https://shop.gestalten.com/products/the-lamborghini-book",
      "published_at": "2026-05-22T21:40:56+02:00",
      "cover": "https://cdn.shopify.com/s/files/1/2717/4124/files/9783961715114_The-Lamborghini-Book_Cover-front_dc67817c-dbe9-4c8b-8061-ff0bc59bfdb6.png?v=1779479166"
    },
    {
      "title": "The Watch Book: Compendium",
      "store": "Gestalten",
      "city": "출판사",
      "section": "디자인",
      "author": "teNeues",
      "store_cover": "https://cdn.shopify.com/s/files/1/2717/4124/files/9783961715022_Watchbook-Compendium_Cover-front_fff329a3-2f01-462c-8339-09d8e0d822c6.png?v=1778682201",
      "store_link": "https://shop.gestalten.com/products/the-watch-book-compendium-revised-edition",
      "published_at": "2026-05-22T20:55:33+02:00",
      "cover": "https://cdn.shopify.com/s/files/1/2717/4124/files/9783961715022_Watchbook-Compendium_Cover-front_fff329a3-2f01-462c-8339-09d8e0d822c6.png?v=1778682201"
    },
    {
      "title": "American Football - The Ultimate Book",
      "store": "Gestalten",
      "city": "출판사",
      "section": "디자인",
      "author": "teNeues",
      "store_cover": "https://cdn.shopify.com/s/files/1/2717/4124/files/AmericanFootballINT_Cover.png?v=1778683258",
      "store_link": "https://shop.gestalten.com/products/american-football-the-ultimate-book",
      "published_at": "2026-05-22T20:51:20+02:00",
      "cover": "https://cdn.shopify.com/s/files/1/2717/4124/files/AmericanFootballINT_Cover.png?v=1778683258"
    },
    {
      "title": "Before They Were Famous",
      "store": "Gestalten",
      "city": "출판사",
      "section": "디자인",
      "author": "teNeues",
      "store_cover": "https://cdn.shopify.com/s/files/1/2717/4124/files/BeforeTheyWereFamous.png?v=1778685165",
      "store_link": "https://shop.gestalten.com/products/before-they-were-famous",
      "published_at": "2026-05-22T20:45:21+02:00",
      "cover": "https://cdn.shopify.com/s/files/1/2717/4124/files/BeforeTheyWereFamous.png?v=1778685165"
    },
    {
      "title": "Treasures from the Patek Philippe Museum",
      "store": "Gestalten",
      "city": "출판사",
      "section": "디자인",
      "author": "teNeues",
      "store_cover": "https://cdn.shopify.com/s/files/1/2717/4124/files/Treasures-from-the-Patek-Philippe-Museum_07.png?v=1779450084",
      "store_link": "https://shop.gestalten.com/products/treasures-from-the-patek-philippe-museum",
      "published_at": "2026-05-22T13:23:34+02:00",
      "cover": "https://cdn.shopify.com/s/files/1/2717/4124/files/Treasures-from-the-Patek-Philippe-Museum_07.png?v=1779450084"
    },
    {
      "title": "Lita Cabellut",
      "store": "Gestalten",
      "city": "출판사",
      "section": "디자인",
      "author": "teNeues",
      "store_cover": "https://cdn.shopify.com/s/files/1/2717/4124/files/LitaCabellut_Cover.png?v=1778680637",
      "store_link": "https://shop.gestalten.com/products/lita-cabellut",
      "published_at": "2026-05-13T15:57:56+02:00",
      "cover": "https://cdn.shopify.com/s/files/1/2717/4124/files/LitaCabellut_Cover.png?v=1778680637"
    },
    {
      "title": "The Stylish Life: Grand Prix",
      "store": "Gestalten",
      "city": "출판사",
      "section": "디자인",
      "author": "teNeues",
      "store_cover": "https://cdn.shopify.com/s/files/1/2717/4124/files/The-Stylish-Life-Grand-Prix_Cover-front.png?v=1760006032",
      "store_link": "https://shop.gestalten.com/products/the-stylish-life-grand-prix",
      "published_at": "2026-05-13T15:57:16+02:00",
      "cover": "https://cdn.shopify.com/s/files/1/2717/4124/files/The-Stylish-Life-Grand-Prix_Cover-front.png?v=1760006032"
    },
    {
      "title": "The Ferrari Book",
      "store": "Gestalten",
      "city": "출판사",
      "section": "디자인",
      "author": "teNeues",
      "store_cover": "https://cdn.shopify.com/s/files/1/2717/4124/files/9783961710201_Cover-Front_1920x1920_38ad4fe8-b05f-48d5-986b-1081a1a94f78.png?v=1778666574",
      "store_link": "https://shop.gestalten.com/products/the-ferrari-book-passion-for-design",
      "published_at": "2026-05-13T15:51:53+02:00",
      "cover": "https://cdn.shopify.com/s/files/1/2717/4124/files/9783961710201_Cover-Front_1920x1920_38ad4fe8-b05f-48d5-986b-1081a1a94f78.png?v=1778666574"
    },
    {
      "title": "Golf - The Ultimate Book",
      "store": "Gestalten",
      "city": "출판사",
      "section": "디자인",
      "author": "teNeues",
      "store_cover": "https://cdn.shopify.com/s/files/1/2717/4124/files/TNGolf_front.png?v=1778570431",
      "store_link": "https://shop.gestalten.com/products/golf-the-ultimate-book",
      "published_at": "2026-05-13T15:48:47+02:00",
      "cover": "https://cdn.shopify.com/s/files/1/2717/4124/files/TNGolf_front.png?v=1778570431"
    },
    {
      "title": "The Stylish Life: Golf",
      "store": "Gestalten",
      "city": "출판사",
      "section": "디자인",
      "author": "teNeues",
      "store_cover": "https://cdn.shopify.com/s/files/1/2717/4124/files/9783832732288_The-Stylish-Life-Golf_Cover-front.png?v=1778491400",
      "store_link": "https://shop.gestalten.com/products/the-stylish-life-golf",
      "published_at": "2026-05-13T15:48:46+02:00",
      "cover": "https://cdn.shopify.com/s/files/1/2717/4124/files/9783832732288_The-Stylish-Life-Golf_Cover-front.png?v=1778491400"
    },
    {
      "title": "Untamed Spirits",
      "store": "Gestalten",
      "city": "출판사",
      "section": "디자인",
      "author": "teNeues",
      "store_cover": "https://cdn.shopify.com/s/files/1/2717/4124/files/Untamed-Spirits_Cover-front.png?v=1760010902",
      "store_link": "https://shop.gestalten.com/products/untamed-spirits-horses-from-around-the-world",
      "published_at": "2026-05-13T15:48:44+02:00",
      "cover": "https://cdn.shopify.com/s/files/1/2717/4124/files/Untamed-Spirits_Cover-front.png?v=1760010902"
    },
    {
      "title": "The Happy Prince and Other Tales",
      "store": "Daunt Books",
      "city": "런던",
      "section": "문학·신간",
      "author": "Oscar Wilde",
      "store_cover": "https://dauntbooks.co.uk/wp-content/uploads/2021/06/9781857159394.jpg",
      "store_link": "https://dauntbooks.co.uk/shop/books/the-happy-prince-and-other-tales-2/",
      "cover": "https://dauntbooks.co.uk/wp-content/uploads/2021/06/9781857159394.jpg"
    },
    {
      "title": "All About Love",
      "store": "Daunt Books",
      "city": "런던",
      "section": "문학·신간",
      "author": "bell hooks",
      "store_cover": "https://dauntbooks.co.uk/wp-content/uploads/2022/04/9780060959470-1.jpg",
      "store_link": "https://dauntbooks.co.uk/shop/books/all-about-love-new-visions/",
      "cover": "https://dauntbooks.co.uk/wp-content/uploads/2022/04/9780060959470-1.jpg"
    },
    {
      "title": "Natives: Race and Class in the Ruins of Empire",
      "store": "Daunt Books",
      "city": "런던",
      "section": "문학·신간",
      "author": "Akala",
      "store_cover": "https://dauntbooks.co.uk/wp-content/uploads/2020/06/9781473661233.jpg",
      "store_link": "https://dauntbooks.co.uk/shop/books/natives-race-and-class-in-the-ruins-of-empire/",
      "cover": "https://dauntbooks.co.uk/wp-content/uploads/2020/06/9781473661233.jpg"
    },
    {
      "title": "The Unwomanly Face of War",
      "store": "Daunt Books",
      "city": "런던",
      "section": "문학·신간",
      "author": "Svetlana Alexievich",
      "store_cover": "https://dauntbooks.co.uk/wp-content/uploads/2022/04/9780141983530.jpg",
      "store_link": "https://dauntbooks.co.uk/shop/books/the-unwomanly-face-of-war/",
      "cover": "https://dauntbooks.co.uk/wp-content/uploads/2022/04/9780141983530.jpg"
    },
    {
      "title": "Winter in the Air",
      "store": "Daunt Books",
      "city": "런던",
      "section": "문학·신간",
      "author": "Sylvia Townsend Warner",
      "store_cover": "https://dauntbooks.co.uk/wp-content/uploads/2022/11/9780571375462.jpg",
      "store_link": "https://dauntbooks.co.uk/shop/books/winter-in-the-air/",
      "cover": "https://dauntbooks.co.uk/wp-content/uploads/2022/11/9780571375462.jpg"
    },
    {
      "title": "A Bite in the Night",
      "store": "Daunt Books",
      "city": "런던",
      "section": "문학·신간",
      "author": "Julian Gough",
      "store_cover": "https://dauntbooks.co.uk/wp-content/uploads/2020/04/9781444921748.jpg",
      "store_link": "https://dauntbooks.co.uk/shop/books/a-bite-in-the-night/",
      "cover": "https://dauntbooks.co.uk/wp-content/uploads/2020/04/9781444921748.jpg"
    },
    {
      "title": "A Sprinkle of Sorcery",
      "store": "Daunt Books",
      "city": "런던",
      "section": "문학·신간",
      "author": "Michelle Harrison",
      "store_cover": "https://dauntbooks.co.uk/wp-content/uploads/2020/05/9781471183867.jpg",
      "store_link": "https://dauntbooks.co.uk/shop/books/a-sprinkle-of-sorcery/",
      "cover": "https://dauntbooks.co.uk/wp-content/uploads/2020/05/9781471183867.jpg"
    },
    {
      "title": "A Tale of Magic",
      "store": "Daunt Books",
      "city": "런던",
      "section": "문학·신간",
      "author": "Chris Colfer",
      "store_cover": "https://dauntbooks.co.uk/wp-content/uploads/2019/11/9781510202115.jpg",
      "store_link": "https://dauntbooks.co.uk/shop/books/a-tale-of-magic/",
      "cover": "https://dauntbooks.co.uk/wp-content/uploads/2019/11/9781510202115.jpg"
    },
    {
      "title": "Agents of the Wild: Operation Honeynut Jennifer Bell",
      "store": "Daunt Books",
      "city": "런던",
      "section": "문학·신간",
      "author": "",
      "store_cover": "https://dauntbooks.co.uk/wp-content/uploads/2020/05/9781406388459.jpg",
      "store_link": "https://dauntbooks.co.uk/shop/books/agents-of-the-wild-operation-honeynut/",
      "cover": "https://dauntbooks.co.uk/wp-content/uploads/2020/05/9781406388459.jpg"
    },
    {
      "title": "Alice",
      "store": "Daunt Books",
      "city": "런던",
      "section": "문학·신간",
      "author": "",
      "store_cover": "https://dauntbooks.co.uk/wp-content/uploads/2020/04/9780141321073.jpg",
      "store_link": "https://dauntbooks.co.uk/shop/books/alices-adventures-in-wonderland-2/",
      "cover": "https://dauntbooks.co.uk/wp-content/uploads/2020/04/9780141321073.jpg"
    },
    {
      "title": "Amelia Fang & The Lost Yeti Treasures",
      "store": "Daunt Books",
      "city": "런던",
      "section": "문학·신간",
      "author": "Laura Ellen Anderson",
      "store_cover": "https://dauntbooks.co.uk/wp-content/uploads/2019/11/9781405293921.jpg",
      "store_link": "https://dauntbooks.co.uk/shop/books/amelia-fang-the-lost-yeti-treasures/",
      "cover": "https://dauntbooks.co.uk/wp-content/uploads/2019/11/9781405293921.jpg"
    },
    {
      "title": "Amelia Fang and The Naughty Caticorns",
      "store": "Daunt Books",
      "city": "런던",
      "section": "문학·신간",
      "author": "Laura Ellen Anderson",
      "store_cover": "https://dauntbooks.co.uk/wp-content/uploads/2020/05/9781405297035.jpg",
      "store_link": "https://dauntbooks.co.uk/shop/books/amelia-fang-and-the-naughty-caticorns/",
      "cover": "https://dauntbooks.co.uk/wp-content/uploads/2020/05/9781405297035.jpg"
    },
    {
      "title": "An Anthology of Intriguing Animals",
      "store": "Daunt Books",
      "city": "런던",
      "section": "문학·신간",
      "author": "Ben Hoare",
      "store_cover": "https://dauntbooks.co.uk/wp-content/uploads/2019/11/9780241334393.jpg",
      "store_link": "https://dauntbooks.co.uk/shop/books/an-anthology-of-intriguing-animals/",
      "cover": "https://dauntbooks.co.uk/wp-content/uploads/2019/11/9780241334393.jpg"
    },
    {
      "title": "Arsenic For Tea",
      "store": "Daunt Books",
      "city": "런던",
      "section": "문학·신간",
      "author": "Robin Stevens",
      "store_cover": "https://dauntbooks.co.uk/wp-content/uploads/2020/05/9780141369792.jpg",
      "store_link": "https://dauntbooks.co.uk/shop/books/arsenic-for-tea/",
      "cover": "https://dauntbooks.co.uk/wp-content/uploads/2020/05/9780141369792.jpg"
    },
    {
      "title": "Art Monsters",
      "store": "Daunt Books",
      "city": "런던",
      "section": "문학·신간",
      "author": "Lauren Elkin",
      "store_cover": "https://dauntbooks.co.uk/wp-content/uploads/2023/12/9781529922554.jpg",
      "store_link": "https://dauntbooks.co.uk/shop/books/art-monsters-unruly-bodies-in-feminist-art/",
      "cover": "https://dauntbooks.co.uk/wp-content/uploads/2023/12/9781529922554.jpg"
    },
    {
      "title": "Asterix and The Chieftain",
      "store": "Daunt Books",
      "city": "런던",
      "section": "문학·신간",
      "author": "",
      "store_cover": "https://dauntbooks.co.uk/wp-content/uploads/2019/11/9781510107137.jpg",
      "store_link": "https://dauntbooks.co.uk/shop/books/asterix-and-the-chieftains-daughter/",
      "cover": "https://dauntbooks.co.uk/wp-content/uploads/2019/11/9781510107137.jpg"
    }
  ],
  "errors": [],
  "total": 136,
  "stores": [
    "Do you read me?!",
    "Donlon Books",
    "Magma Books",
    "Mast Books",
    "Phaidon",
    "Gestalten",
    "Daunt Books"
  ]
}